navigator_auth/__init__.py
navigator_auth/auth.py
navigator_auth/conf.py
navigator_auth/decorators.py
navigator_auth/exceptions.c
navigator_auth/exceptions.cpython-313-x86_64-linux-gnu.so
navigator_auth/exceptions.pxd
navigator_auth/exceptions.pyx
navigator_auth/identities.py
navigator_auth/models.py
navigator_auth/py.typed
navigator_auth/responses.py
navigator_auth/templates.py
navigator_auth/uv.py
navigator_auth/version.py
navigator_auth/abac/__init__.py
navigator_auth/abac/audit.py
navigator_auth/abac/context.py
navigator_auth/abac/decorators.py
navigator_auth/abac/errors.py
navigator_auth/abac/guardian.py
navigator_auth/abac/middleware.py
navigator_auth/abac/pdp.py
navigator_auth/abac/policyhandler.py
navigator_auth/abac/policies/__init__.py
navigator_auth/abac/policies/abstract.py
navigator_auth/abac/policies/environment.py
navigator_auth/abac/policies/evaluator.py
navigator_auth/abac/policies/file.py
navigator_auth/abac/policies/obj.py
navigator_auth/abac/policies/policy.py
navigator_auth/abac/policies/resource_policy.py
navigator_auth/abac/policies/resources.py
navigator_auth/abac/storages/__init__.py
navigator_auth/abac/storages/abstract.py
navigator_auth/abac/storages/db.py
navigator_auth/abac/storages/pg.py
navigator_auth/authorizations/__init__.py
navigator_auth/authorizations/abstract.py
navigator_auth/authorizations/allow_hosts.py
navigator_auth/authorizations/hosts.py
navigator_auth/authorizations/useragent.py
navigator_auth/backends/__init__.py
navigator_auth/backends/abstract.py
navigator_auth/backends/adfs.py
navigator_auth/backends/api.py
navigator_auth/backends/azure.py
navigator_auth/backends/basic.py
navigator_auth/backends/django.py
navigator_auth/backends/external.py
navigator_auth/backends/github.py
navigator_auth/backends/google.py
navigator_auth/backends/jwksutils.py
navigator_auth/backends/noauth.py
navigator_auth/backends/oauth.py
navigator_auth/backends/okta.py
navigator_auth-0.17.2.dist-info/METADATA
navigator_auth-0.17.2.dist-info/WHEEL
navigator_auth-0.17.2.dist-info/top_level.txt
navigator_auth-0.17.2.dist-info/RECORD
navigator_auth-0.17.2.dist-info/licenses/LICENSE
